sphinx_autopackagesummary.py
sphinx_autopackagesummary-1.2.dist-info/METADATA
sphinx_autopackagesummary-1.2.dist-info/WHEEL
sphinx_autopackagesummary-1.2.dist-info/top_level.txt
sphinx_autopackagesummary-1.2.dist-info/RECORD
