Metadata-Version: 2.1
Name: sphinx-autopackagesummary
Version: 1.2
Summary: Sphinx extension to automatically generate autosummary tables for Python packages
Home-page: https://github.com/rdb/sphinx-autopackagesummary
Author: rdb
Author-email: me@rdb.name
License: UNKNOWN
Platform: UNKNOWN
Classifier: Programming Language :: Python :: 3
Classifier: Operating System :: OS Independent
Classifier: Framework :: Sphinx
Classifier: Topic :: Documentation
Classifier: Topic :: Software Development :: Documentation
Classifier: License :: Public Domain
Requires-Dist: sphinx
